[
    {
        "orderId": 1,
        "customer": {
            "customerId": 1004,
            "name": "Bob White",
            "email": "bobwhite@example.com",
            "phone": "+1234567893",
            "address": {
                "street": "477 Main St",
                "city": "New York",
                "state": "NY",
                "zipcode": "99122",
                "country": "USA"
            }
        },
        "orderDate": "2024-10-26T21:44:17Z",
        "deliveryDate": "2024-10-30T21:44:17Z",
        "status": "Shipped",
        "items": [
            {
                "productId": 103,
                "productName": "Kids' Warm Jacket",
                "quantity": 2,
                "price": 49.99,
                "totalPrice": 199.96
            },
            {
                "productId": 101,
                "productName": "Men's Casual Shirt",
                "quantity": 3,
                "price": 35.99,
                "totalPrice": 179.95
            },
            {
                "productId": 105,
                "productName": "Women's Woolen Coat",
                "quantity": 4,
                "price": 120.0,
                "totalPrice": 600.0
            }
        ],
        "payment": {
            "method": "PayPal",
            "transactionId": "TX319759823",
            "totalAmount": 979.91,
            "currency": "USD"
        }
    },
    {
        "orderId": 2,
        "customer": {
            "customerId": 1001,
            "name": "John Doe",
            "email": "johndoe@example.com",
            "phone": "+1234567890",
            "address": {
                "street": "352 Main St",
                "city": "New York",
                "state": "NY",
                "zipcode": "69024",
                "country": "USA"
            }
        },
        "orderDate": "2024-11-15T21:44:17Z",
        "deliveryDate": "2024-11-19T21:44:17Z",
        "status": "Pending",
        "items": [
            {
                "productId": 104,
                "productName": "Men's Running Pants",
                "quantity": 1,
                "price": 59.99,
                "totalPrice": 299.95
            },
            {
                "productId": 105,
                "productName": "Women's Woolen Coat",
                "quantity": 4,
                "price": 120.0,
                "totalPrice": 240.0
            }
        ],
        "payment": {
            "method": "Cash on Delivery",
            "transactionId": "TX418947131",
            "totalAmount": 539.95,
            "currency": "USD"
        }
    },
    {
        "orderId": 3,
        "customer": {
            "customerId": 1002,
            "name": "Jane Smith",
            "email": "janesmith@example.com",
            "phone": "+1234567891",
            "address": {
                "street": "508 Main St",
                "city": "New York",
                "state": "NY",
                "zipcode": "85137",
                "country": "USA"
            }
        },
        "orderDate": "2024-11-01T21:44:17Z",
        "deliveryDate": "2024-11-09T21:44:17Z",
        "status": "Cancelled",
        "items": [
            {
                "productId": 101,
                "productName": "Men's Casual Shirt",
                "quantity": 3,
                "price": 35.99,
                "totalPrice": 107.97
            },
            {
                "productId": 102,
                "productName": "Women's Evening Dress",
                "quantity": 2,
                "price": 89.99,
                "totalPrice": 359.96
            },
            {
                "productId": 103,
                "productName": "Kids' Warm Jacket",
                "quantity": 5,
                "price": 49.99,
                "totalPrice": 99.98
            }
        ],
        "payment": {
            "method": "PayPal",
            "transactionId": "TX295742942",
            "totalAmount": 567.91,
            "currency": "USD"
        }
    },
    {
        "orderId": 4,
        "customer": {
            "customerId": 1002,
            "name": "Jane Smith",
            "email": "janesmith@example.com",
            "phone": "+1234567891",
            "address": {
                "street": "435 Main St",
                "city": "New York",
                "state": "NY",
                "zipcode": "90766",
                "country": "USA"
            }
        },
        "orderDate": "2024-10-27T21:44:17Z",
        "deliveryDate": "2024-10-31T21:44:17Z",
        "status": "Pending",
        "items": [
            {
                "productId": 103,
                "productName": "Kids' Warm Jacket",
                "quantity": 2,
                "price": 49.99,
                "totalPrice": 149.97
            },
            {
                "productId": 105,
                "productName": "Women's Woolen Coat",
                "quantity": 1,
                "price": 120.0,
                "totalPrice": 600.0
            },
            {
                "productId": 101,
                "productName": "Men's Casual Shirt",
                "quantity": 2,
                "price": 35.99,
                "totalPrice": 143.96
            }
        ],
        "payment": {
            "method": "Credit Card",
            "transactionId": "TX183553269",
            "totalAmount": 893.93,
            "currency": "USD"
        }
    },
    {
        "orderId": 5,
        "customer": {
            "customerId": 1003,
            "name": "Alice Brown",
            "email": "alicebrown@example.com",
            "phone": "+1234567892",
            "address": {
                "street": "748 Main St",
                "city": "New York",
                "state": "NY",
                "zipcode": "53384",
                "country": "USA"
            }
        },
        "orderDate": "2024-11-07T21:44:17Z",
        "deliveryDate": "2024-11-17T21:44:17Z",
        "status": "Delivered",
        "items": [
            {
                "productId": 105,
                "productName": "Women's Woolen Coat",
                "quantity": 1,
                "price": 120.0,
                "totalPrice": 240.0
            },
            {
                "productId": 101,
                "productName": "Men's Casual Shirt",
                "quantity": 4,
                "price": 35.99,
                "totalPrice": 107.97
            },
            {
                "productId": 103,
                "productName": "Kids' Warm Jacket",
                "quantity": 4,
                "price": 49.99,
                "totalPrice": 199.96
            }
        ],
        "payment": {
            "method": "Credit Card",
            "transactionId": "TX840258886",
            "totalAmount": 547.93,
            "currency": "USD"
        }
    },
    {
        "orderId": 6,
        "customer": {
            "customerId": 1003,
            "name": "Alice Brown",
            "email": "alicebrown@example.com",
            "phone": "+1234567892",
            "address": {
                "street": "150 Main St",
                "city": "New York",
                "state": "NY",
                "zipcode": "89928",
                "country": "USA"
            }
        },
        "orderDate": "2024-10-29T21:44:17Z",
        "deliveryDate": "2024-11-04T21:44:17Z",
        "status": "Pending",
        "items": [
            {
                "productId": 105,
                "productName": "Women's Woolen Coat",
                "quantity": 2,
                "price": 120.0,
                "totalPrice": 120.0
            },
            {
                "productId": 101,
                "productName": "Men's Casual Shirt",
                "quantity": 3,
                "price": 35.99,
                "totalPrice": 107.97
            },
            {
                "productId": 103,
                "productName": "Kids' Warm Jacket",
                "quantity": 2,
                "price": 49.99,
                "totalPrice": 249.95
            }
        ],
        "payment": {
            "method": "Credit Card",
            "transactionId": "TX139820035",
            "totalAmount": 477.92,
            "currency": "USD"
        }
    },
    {
        "orderId": 7,
        "customer": {
            "customerId": 1004,
            "name": "Bob White",
            "email": "bobwhite@example.com",
            "phone": "+1234567893",
            "address": {
                "street": "365 Main St",
                "city": "New York",
                "state": "NY",
                "zipcode": "33561",
                "country": "USA"
            }
        },
        "orderDate": "2024-11-13T21:44:17Z",
        "deliveryDate": "2024-11-22T21:44:17Z",
        "status": "Shipped",
        "items": [
            {
                "productId": 103,
                "productName": "Kids' Warm Jacket",
                "quantity": 5,
                "price": 49.99,
                "totalPrice": 99.98
            },
            {
                "productId": 104,
                "productName": "Men's Running Pants",
                "quantity": 2,
                "price": 59.99,
                "totalPrice": 179.97
            },
            {
                "productId": 101,
                "productName": "Men's Casual Shirt",
                "quantity": 4,
                "price": 35.99,
                "totalPrice": 71.98
            }
        ],
        "payment": {
            "method": "Cash on Delivery",
            "transactionId": "TX303609605",
            "totalAmount": 351.93,
            "currency": "USD"
        }
    },
    {
        "orderId": 8,
        "customer": {
            "customerId": 1004,
            "name": "Bob White",
            "email": "bobwhite@example.com",
            "phone": "+1234567893",
            "address": {
                "street": "849 Main St",
                "city": "New York",
                "state": "NY",
                "zipcode": "55631",
                "country": "USA"
            }
        },
        "orderDate": "2024-10-31T21:44:17Z",
        "deliveryDate": "2024-11-08T21:44:17Z",
        "status": "Delivered",
        "items": [
            {
                "productId": 102,
                "productName": "Women's Evening Dress",
                "quantity": 2,
                "price": 89.99,
                "totalPrice": 359.96
            }
        ],
        "payment": {
            "method": "PayPal",
            "transactionId": "TX815411705",
            "totalAmount": 359.96,
            "currency": "USD"
        }
    },
    {
        "orderId": 9,
        "customer": {
            "customerId": 1005,
            "name": "Charlie Black",
            "email": "charlieblack@example.com",
            "phone": "+1234567894",
            "address": {
                "street": "116 Main St",
                "city": "New York",
                "state": "NY",
                "zipcode": "88465",
                "country": "USA"
            }
        },
        "orderDate": "2024-10-22T21:44:17Z",
        "deliveryDate": "2024-10-31T21:44:17Z",
        "status": "Pending",
        "items": [
            {
                "productId": 103,
                "productName": "Kids' Warm Jacket",
                "quantity": 1,
                "price": 49.99,
                "totalPrice": 49.99
            },
            {
                "productId": 102,
                "productName": "Women's Evening Dress",
                "quantity": 5,
                "price": 89.99,
                "totalPrice": 179.98
            },
            {
                "productId": 101,
                "productName": "Men's Casual Shirt",
                "quantity": 5,
                "price": 35.99,
                "totalPrice": 71.98
            }
        ],
        "payment": {
            "method": "Credit Card",
            "transactionId": "TX681163153",
            "totalAmount": 301.95,
            "currency": "USD"
        }
    },
    {
        "orderId": 10,
        "customer": {
            "customerId": 1001,
            "name": "John Doe",
            "email": "johndoe@example.com",
            "phone": "+1234567890",
            "address": {
                "street": "305 Main St",
                "city": "New York",
                "state": "NY",
                "zipcode": "93151",
                "country": "USA"
            }
        },
        "orderDate": "2024-10-25T21:44:17Z",
        "deliveryDate": "2024-11-02T21:44:17Z",
        "status": "Pending",
        "items": [
            {
                "productId": 104,
                "productName": "Men's Running Pants",
                "quantity": 1,
                "price": 59.99,
                "totalPrice": 179.97
            },
            {
                "productId": 105,
                "productName": "Women's Woolen Coat",
                "quantity": 3,
                "price": 120.0,
                "totalPrice": 240.0
            }
        ],
        "payment": {
            "method": "Credit Card",
            "transactionId": "TX707701628",
            "totalAmount": 419.97,
            "currency": "USD"
        }
    },
    {
        "orderId": 11,
        "customer": {
            "customerId": 1004,
            "name": "Bob White",
            "email": "bobwhite@example.com",
            "phone": "+1234567893",
            "address": {
                "street": "309 Main St",
                "city": "New York",
                "state": "NY",
                "zipcode": "52211",
                "country": "USA"
            }
        },
        "orderDate": "2024-11-13T21:44:17Z",
        "deliveryDate": "2024-11-20T21:44:17Z",
        "status": "Cancelled",
        "items": [
            {
                "productId": 101,
                "productName": "Men's Casual Shirt",
                "quantity": 4,
                "price": 35.99,
                "totalPrice": 179.95
            },
            {
                "productId": 102,
                "productName": "Women's Evening Dress",
                "quantity": 4,
                "price": 89.99,
                "totalPrice": 89.99
            },
            {
                "productId": 103,
                "productName": "Kids' Warm Jacket",
                "quantity": 1,
                "price": 49.99,
                "totalPrice": 99.98
            }
        ],
        "payment": {
            "method": "PayPal",
            "transactionId": "TX242410120",
            "totalAmount": 369.92,
            "currency": "USD"
        }
    },
    {
        "orderId": 12,
        "customer": {
            "customerId": 1002,
            "name": "Jane Smith",
            "email": "janesmith@example.com",
            "phone": "+1234567891",
            "address": {
                "street": "300 Main St",
                "city": "New York",
                "state": "NY",
                "zipcode": "14568",
                "country": "USA"
            }
        },
        "orderDate": "2024-10-21T21:44:17Z",
        "deliveryDate": "2024-10-26T21:44:17Z",
        "status": "Cancelled",
        "items": [
            {
                "productId": 102,
                "productName": "Women's Evening Dress",
                "quantity": 3,
                "price": 89.99,
                "totalPrice": 269.97
            },
            {
                "productId": 101,
                "productName": "Men's Casual Shirt",
                "quantity": 4,
                "price": 35.99,
                "totalPrice": 35.99
            },
            {
                "productId": 104,
                "productName": "Men's Running Pants",
                "quantity": 2,
                "price": 59.99,
                "totalPrice": 239.96
            }
        ],
        "payment": {
            "method": "PayPal",
            "transactionId": "TX703895924",
            "totalAmount": 545.92,
            "currency": "USD"
        }
    },
    {
        "orderId": 13,
        "customer": {
            "customerId": 1001,
            "name": "John Doe",
            "email": "johndoe@example.com",
            "phone": "+1234567890",
            "address": {
                "street": "971 Main St",
                "city": "New York",
                "state": "NY",
                "zipcode": "54531",
                "country": "USA"
            }
        },
        "orderDate": "2024-10-29T21:44:17Z",
        "deliveryDate": "2024-11-07T21:44:17Z",
        "status": "Cancelled",
        "items": [
            {
                "productId": 103,
                "productName": "Kids' Warm Jacket",
                "quantity": 1,
                "price": 49.99,
                "totalPrice": 249.95
            }
        ],
        "payment": {
            "method": "PayPal",
            "transactionId": "TX529616855",
            "totalAmount": 249.95,
            "currency": "USD"
        }
    },
    {
        "orderId": 14,
        "customer": {
            "customerId": 1002,
            "name": "Jane Smith",
            "email": "janesmith@example.com",
            "phone": "+1234567891",
            "address": {
                "street": "922 Main St",
                "city": "New York",
                "state": "NY",
                "zipcode": "49773",
                "country": "USA"
            }
        },
        "orderDate": "2024-11-14T21:44:17Z",
        "deliveryDate": "2024-11-20T21:44:17Z",
        "status": "Pending",
        "items": [
            {
                "productId": 102,
                "productName": "Women's Evening Dress",
                "quantity": 2,
                "price": 89.99,
                "totalPrice": 179.98
            },
            {
                "productId": 105,
                "productName": "Women's Woolen Coat",
                "quantity": 4,
                "price": 120.0,
                "totalPrice": 600.0
            }
        ],
        "payment": {
            "method": "Credit Card",
            "transactionId": "TX436859132",
            "totalAmount": 779.98,
            "currency": "USD"
        }
    },
    {
        "orderId": 15,
        "customer": {
            "customerId": 1005,
            "name": "Charlie Black",
            "email": "charlieblack@example.com",
            "phone": "+1234567894",
            "address": {
                "street": "971 Main St",
                "city": "New York",
                "state": "NY",
                "zipcode": "50949",
                "country": "USA"
            }
        },
        "orderDate": "2024-11-12T21:44:17Z",
        "deliveryDate": "2024-11-16T21:44:17Z",
        "status": "Shipped",
        "items": [
            {
                "productId": 104,
                "productName": "Men's Running Pants",
                "quantity": 3,
                "price": 59.99,
                "totalPrice": 119.98
            },
            {
                "productId": 102,
                "productName": "Women's Evening Dress",
                "quantity": 3,
                "price": 89.99,
                "totalPrice": 179.98
            }
        ],
        "payment": {
            "method": "Cash on Delivery",
            "transactionId": "TX709338633",
            "totalAmount": 299.96,
            "currency": "USD"
        }
    },
    {
        "orderId": 16,
        "customer": {
            "customerId": 1001,
            "name": "John Doe",
            "email": "johndoe@example.com",
            "phone": "+1234567890",
            "address": {
                "street": "702 Main St",
                "city": "New York",
                "state": "NY",
                "zipcode": "61571",
                "country": "USA"
            }
        },
        "orderDate": "2024-10-25T21:44:17Z",
        "deliveryDate": "2024-11-01T21:44:17Z",
        "status": "Cancelled",
        "items": [
            {
                "productId": 105,
                "productName": "Women's Woolen Coat",
                "quantity": 3,
                "price": 120.0,
                "totalPrice": 360.0
            },
            {
                "productId": 102,
                "productName": "Women's Evening Dress",
                "quantity": 5,
                "price": 89.99,
                "totalPrice": 359.96
            },
            {
                "productId": 103,
                "productName": "Kids' Warm Jacket",
                "quantity": 1,
                "price": 49.99,
                "totalPrice": 49.99
            }
        ],
        "payment": {
            "method": "Credit Card",
            "transactionId": "TX947989055",
            "totalAmount": 769.95,
            "currency": "USD"
        }
    },
    {
        "orderId": 17,
        "customer": {
            "customerId": 1002,
            "name": "Jane Smith",
            "email": "janesmith@example.com",
            "phone": "+1234567891",
            "address": {
                "street": "102 Main St",
                "city": "New York",
                "state": "NY",
                "zipcode": "31726",
                "country": "USA"
            }
        },
        "orderDate": "2024-11-06T21:44:17Z",
        "deliveryDate": "2024-11-10T21:44:17Z",
        "status": "Pending",
        "items": [
            {
                "productId": 104,
                "productName": "Men's Running Pants",
                "quantity": 4,
                "price": 59.99,
                "totalPrice": 299.95
            },
            {
                "productId": 105,
                "productName": "Women's Woolen Coat",
                "quantity": 1,
                "price": 120.0,
                "totalPrice": 240.0
            },
            {
                "productId": 101,
                "productName": "Men's Casual Shirt",
                "quantity": 4,
                "price": 35.99,
                "totalPrice": 35.99
            }
        ],
        "payment": {
            "method": "Credit Card",
            "transactionId": "TX737131634",
            "totalAmount": 575.94,
            "currency": "USD"
        }
    },
    {
        "orderId": 18,
        "customer": {
            "customerId": 1005,
            "name": "Charlie Black",
            "email": "charlieblack@example.com",
            "phone": "+1234567894",
            "address": {
                "street": "88 Main St",
                "city": "New York",
                "state": "NY",
                "zipcode": "24079",
                "country": "USA"
            }
        },
        "orderDate": "2024-11-09T21:44:17Z",
        "deliveryDate": "2024-11-15T21:44:17Z",
        "status": "Cancelled",
        "items": [
            {
                "productId": 105,
                "productName": "Women's Woolen Coat",
                "quantity": 5,
                "price": 120.0,
                "totalPrice": 240.0
            }
        ],
        "payment": {
            "method": "Cash on Delivery",
            "transactionId": "TX608915728",
            "totalAmount": 240.0,
            "currency": "USD"
        }
    },
    {
        "orderId": 19,
        "customer": {
            "customerId": 1005,
            "name": "Charlie Black",
            "email": "charlieblack@example.com",
            "phone": "+1234567894",
            "address": {
                "street": "22 Main St",
                "city": "New York",
                "state": "NY",
                "zipcode": "98581",
                "country": "USA"
            }
        },
        "orderDate": "2024-11-14T21:44:17Z",
        "deliveryDate": "2024-11-24T21:44:17Z",
        "status": "Delivered",
        "items": [
            {
                "productId": 103,
                "productName": "Kids' Warm Jacket",
                "quantity": 3,
                "price": 49.99,
                "totalPrice": 199.96
            },
            {
                "productId": 105,
                "productName": "Women's Woolen Coat",
                "quantity": 5,
                "price": 120.0,
                "totalPrice": 600.0
            },
            {
                "productId": 101,
                "productName": "Men's Casual Shirt",
                "quantity": 2,
                "price": 35.99,
                "totalPrice": 71.98
            }
        ],
        "payment": {
            "method": "Credit Card",
            "transactionId": "TX449830475",
            "totalAmount": 871.94,
            "currency": "USD"
        }
    },
    {
        "orderId": 20,
        "customer": {
            "customerId": 1003,
            "name": "Alice Brown",
            "email": "alicebrown@example.com",
            "phone": "+1234567892",
            "address": {
                "street": "593 Main St",
                "city": "New York",
                "state": "NY",
                "zipcode": "84357",
                "country": "USA"
            }
        },
        "orderDate": "2024-10-26T21:44:17Z",
        "deliveryDate": "2024-11-03T21:44:17Z",
        "status": "Delivered",
        "items": [
            {
                "productId": 103,
                "productName": "Kids' Warm Jacket",
                "quantity": 2,
                "price": 49.99,
                "totalPrice": 49.99
            }
        ],
        "payment": {
            "method": "PayPal",
            "transactionId": "TX570454455",
            "totalAmount": 49.99,
            "currency": "USD"
        }
    },
    {
        "orderId": 21,
        "customer": {
            "customerId": 1001,
            "name": "John Doe",
            "email": "johndoe@example.com",
            "phone": "+1234567890",
            "address": {
                "street": "483 Main St",
                "city": "New York",
                "state": "NY",
                "zipcode": "58990",
                "country": "USA"
            }
        },
        "orderDate": "2024-11-08T21:44:17Z",
        "deliveryDate": "2024-11-12T21:44:17Z",
        "status": "Cancelled",
        "items": [
            {
                "productId": 104,
                "productName": "Men's Running Pants",
                "quantity": 5,
                "price": 59.99,
                "totalPrice": 59.99
            }
        ],
        "payment": {
            "method": "PayPal",
            "transactionId": "TX567050741",
            "totalAmount": 59.99,
            "currency": "USD"
        }
    },
    {
        "orderId": 22,
        "customer": {
            "customerId": 1002,
            "name": "Jane Smith",
            "email": "janesmith@example.com",
            "phone": "+1234567891",
            "address": {
                "street": "653 Main St",
                "city": "New York",
                "state": "NY",
                "zipcode": "57605",
                "country": "USA"
            }
        },
        "orderDate": "2024-11-10T21:44:17Z",
        "deliveryDate": "2024-11-20T21:44:17Z",
        "status": "Delivered",
        "items": [
            {
                "productId": 104,
                "productName": "Men's Running Pants",
                "quantity": 5,
                "price": 59.99,
                "totalPrice": 179.97
            },
            {
                "productId": 105,
                "productName": "Women's Woolen Coat",
                "quantity": 3,
                "price": 120.0,
                "totalPrice": 600.0
            }
        ],
        "payment": {
            "method": "Cash on Delivery",
            "transactionId": "TX923301045",
            "totalAmount": 779.97,
            "currency": "USD"
        }
    },
    {
        "orderId": 23,
        "customer": {
            "customerId": 1004,
            "name": "Bob White",
            "email": "bobwhite@example.com",
            "phone": "+1234567893",
            "address": {
                "street": "573 Main St",
                "city": "New York",
                "state": "NY",
                "zipcode": "68940",
                "country": "USA"
            }
        },
        "orderDate": "2024-11-01T21:44:17Z",
        "deliveryDate": "2024-11-05T21:44:17Z",
        "status": "Cancelled",
        "items": [
            {
                "productId": 101,
                "productName": "Men's Casual Shirt",
                "quantity": 2,
                "price": 35.99,
                "totalPrice": 179.95
            }
        ],
        "payment": {
            "method": "PayPal",
            "transactionId": "TX889769106",
            "totalAmount": 179.95,
            "currency": "USD"
        }
    },
    {
        "orderId": 24,
        "customer": {
            "customerId": 1005,
            "name": "Charlie Black",
            "email": "charlieblack@example.com",
            "phone": "+1234567894",
            "address": {
                "street": "811 Main St",
                "city": "New York",
                "state": "NY",
                "zipcode": "83934",
                "country": "USA"
            }
        },
        "orderDate": "2024-11-09T21:44:17Z",
        "deliveryDate": "2024-11-18T21:44:17Z",
        "status": "Pending",
        "items": [
            {
                "productId": 104,
                "productName": "Men's Running Pants",
                "quantity": 1,
                "price": 59.99,
                "totalPrice": 119.98
            }
        ],
        "payment": {
            "method": "PayPal",
            "transactionId": "TX453684363",
            "totalAmount": 119.98,
            "currency": "USD"
        }
    },
    {
        "orderId": 25,
        "customer": {
            "customerId": 1003,
            "name": "Alice Brown",
            "email": "alicebrown@example.com",
            "phone": "+1234567892",
            "address": {
                "street": "346 Main St",
                "city": "New York",
                "state": "NY",
                "zipcode": "69172",
                "country": "USA"
            }
        },
        "orderDate": "2024-10-22T21:44:17Z",
        "deliveryDate": "2024-10-30T21:44:17Z",
        "status": "Cancelled",
        "items": [
            {
                "productId": 104,
                "productName": "Men's Running Pants",
                "quantity": 4,
                "price": 59.99,
                "totalPrice": 239.96
            },
            {
                "productId": 105,
                "productName": "Women's Woolen Coat",
                "quantity": 2,
                "price": 120.0,
                "totalPrice": 600.0
            },
            {
                "productId": 102,
                "productName": "Women's Evening Dress",
                "quantity": 5,
                "price": 89.99,
                "totalPrice": 89.99
            }
        ],
        "payment": {
            "method": "Cash on Delivery",
            "transactionId": "TX142046038",
            "totalAmount": 929.95,
            "currency": "USD"
        }
    },
    {
        "orderId": 26,
        "customer": {
            "customerId": 1005,
            "name": "Charlie Black",
            "email": "charlieblack@example.com",
            "phone": "+1234567894",
            "address": {
                "street": "556 Main St",
                "city": "New York",
                "state": "NY",
                "zipcode": "22129",
                "country": "USA"
            }
        },
        "orderDate": "2024-10-27T21:44:17Z",
        "deliveryDate": "2024-10-30T21:44:17Z",
        "status": "Shipped",
        "items": [
            {
                "productId": 103,
                "productName": "Kids' Warm Jacket",
                "quantity": 3,
                "price": 49.99,
                "totalPrice": 149.97
            },
            {
                "productId": 104,
                "productName": "Men's Running Pants",
                "quantity": 3,
                "price": 59.99,
                "totalPrice": 59.99
            },
            {
                "productId": 101,
                "productName": "Men's Casual Shirt",
                "quantity": 5,
                "price": 35.99,
                "totalPrice": 143.96
            }
        ],
        "payment": {
            "method": "Credit Card",
            "transactionId": "TX681824099",
            "totalAmount": 353.92,
            "currency": "USD"
        }
    },
    {
        "orderId": 27,
        "customer": {
            "customerId": 1001,
            "name": "John Doe",
            "email": "johndoe@example.com",
            "phone": "+1234567890",
            "address": {
                "street": "794 Main St",
                "city": "New York",
                "state": "NY",
                "zipcode": "88301",
                "country": "USA"
            }
        },
        "orderDate": "2024-11-14T21:44:17Z",
        "deliveryDate": "2024-11-21T21:44:17Z",
        "status": "Delivered",
        "items": [
            {
                "productId": 103,
                "productName": "Kids' Warm Jacket",
                "quantity": 1,
                "price": 49.99,
                "totalPrice": 149.97
            },
            {
                "productId": 105,
                "productName": "Women's Woolen Coat",
                "quantity": 5,
                "price": 120.0,
                "totalPrice": 600.0
            }
        ],
        "payment": {
            "method": "Cash on Delivery",
            "transactionId": "TX933444799",
            "totalAmount": 749.97,
            "currency": "USD"
        }
    },
    {
        "orderId": 28,
        "customer": {
            "customerId": 1004,
            "name": "Bob White",
            "email": "bobwhite@example.com",
            "phone": "+1234567893",
            "address": {
                "street": "295 Main St",
                "city": "New York",
                "state": "NY",
                "zipcode": "10668",
                "country": "USA"
            }
        },
        "orderDate": "2024-10-29T21:44:17Z",
        "deliveryDate": "2024-11-06T21:44:17Z",
        "status": "Delivered",
        "items": [
            {
                "productId": 104,
                "productName": "Men's Running Pants",
                "quantity": 1,
                "price": 59.99,
                "totalPrice": 299.95
            }
        ],
        "payment": {
            "method": "Cash on Delivery",
            "transactionId": "TX754205801",
            "totalAmount": 299.95,
            "currency": "USD"
        }
    },
    {
        "orderId": 29,
        "customer": {
            "customerId": 1005,
            "name": "Charlie Black",
            "email": "charlieblack@example.com",
            "phone": "+1234567894",
            "address": {
                "street": "164 Main St",
                "city": "New York",
                "state": "NY",
                "zipcode": "79195",
                "country": "USA"
            }
        },
        "orderDate": "2024-10-30T21:44:17Z",
        "deliveryDate": "2024-11-08T21:44:17Z",
        "status": "Cancelled",
        "items": [
            {
                "productId": 105,
                "productName": "Women's Woolen Coat",
                "quantity": 2,
                "price": 120.0,
                "totalPrice": 600.0
            },
            {
                "productId": 104,
                "productName": "Men's Running Pants",
                "quantity": 2,
                "price": 59.99,
                "totalPrice": 179.97
            }
        ],
        "payment": {
            "method": "Credit Card",
            "transactionId": "TX808936018",
            "totalAmount": 779.97,
            "currency": "USD"
        }
    },
    {
        "orderId": 30,
        "customer": {
            "customerId": 1001,
            "name": "John Doe",
            "email": "johndoe@example.com",
            "phone": "+1234567890",
            "address": {
                "street": "566 Main St",
                "city": "New York",
                "state": "NY",
                "zipcode": "58006",
                "country": "USA"
            }
        },
        "orderDate": "2024-11-09T21:44:17Z",
        "deliveryDate": "2024-11-16T21:44:17Z",
        "status": "Cancelled",
        "items": [
            {
                "productId": 101,
                "productName": "Men's Casual Shirt",
                "quantity": 2,
                "price": 35.99,
                "totalPrice": 143.96
            },
            {
                "productId": 103,
                "productName": "Kids' Warm Jacket",
                "quantity": 5,
                "price": 49.99,
                "totalPrice": 249.95
            }
        ],
        "payment": {
            "method": "Credit Card",
            "transactionId": "TX318128563",
            "totalAmount": 393.91,
            "currency": "USD"
        }
    },
    {
        "orderId": 31,
        "customer": {
            "customerId": 1004,
            "name": "Bob White",
            "email": "bobwhite@example.com",
            "phone": "+1234567893",
            "address": {
                "street": "413 Main St",
                "city": "New York",
                "state": "NY",
                "zipcode": "75940",
                "country": "USA"
            }
        },
        "orderDate": "2024-10-27T21:44:17Z",
        "deliveryDate": "2024-10-31T21:44:17Z",
        "status": "Delivered",
        "items": [
            {
                "productId": 102,
                "productName": "Women's Evening Dress",
                "quantity": 4,
                "price": 89.99,
                "totalPrice": 89.99
            }
        ],
        "payment": {
            "method": "PayPal",
            "transactionId": "TX173896598",
            "totalAmount": 89.99,
            "currency": "USD"
        }
    },
    {
        "orderId": 32,
        "customer": {
            "customerId": 1005,
            "name": "Charlie Black",
            "email": "charlieblack@example.com",
            "phone": "+1234567894",
            "address": {
                "street": "609 Main St",
                "city": "New York",
                "state": "NY",
                "zipcode": "82548",
                "country": "USA"
            }
        },
        "orderDate": "2024-11-11T21:44:17Z",
        "deliveryDate": "2024-11-18T21:44:17Z",
        "status": "Delivered",
        "items": [
            {
                "productId": 104,
                "productName": "Men's Running Pants",
                "quantity": 2,
                "price": 59.99,
                "totalPrice": 299.95
            },
            {
                "productId": 101,
                "productName": "Men's Casual Shirt",
                "quantity": 5,
                "price": 35.99,
                "totalPrice": 71.98
            },
            {
                "productId": 103,
                "productName": "Kids' Warm Jacket",
                "quantity": 4,
                "price": 49.99,
                "totalPrice": 249.95
            }
        ],
        "payment": {
            "method": "Cash on Delivery",
            "transactionId": "TX503329727",
            "totalAmount": 621.88,
            "currency": "USD"
        }
    },
    {
        "orderId": 33,
        "customer": {
            "customerId": 1005,
            "name": "Charlie Black",
            "email": "charlieblack@example.com",
            "phone": "+1234567894",
            "address": {
                "street": "969 Main St",
                "city": "New York",
                "state": "NY",
                "zipcode": "71024",
                "country": "USA"
            }
        },
        "orderDate": "2024-11-06T21:44:17Z",
        "deliveryDate": "2024-11-09T21:44:17Z",
        "status": "Delivered",
        "items": [
            {
                "productId": 101,
                "productName": "Men's Casual Shirt",
                "quantity": 4,
                "price": 35.99,
                "totalPrice": 71.98
            },
            {
                "productId": 105,
                "productName": "Women's Woolen Coat",
                "quantity": 4,
                "price": 120.0,
                "totalPrice": 240.0
            },
            {
                "productId": 103,
                "productName": "Kids' Warm Jacket",
                "quantity": 4,
                "price": 49.99,
                "totalPrice": 249.95
            }
        ],
        "payment": {
            "method": "Cash on Delivery",
            "transactionId": "TX839442285",
            "totalAmount": 561.93,
            "currency": "USD"
        }
    },
    {
        "orderId": 34,
        "customer": {
            "customerId": 1002,
            "name": "Jane Smith",
            "email": "janesmith@example.com",
            "phone": "+1234567891",
            "address": {
                "street": "339 Main St",
                "city": "New York",
                "state": "NY",
                "zipcode": "18590",
                "country": "USA"
            }
        },
        "orderDate": "2024-10-19T21:44:17Z",
        "deliveryDate": "2024-10-29T21:44:17Z",
        "status": "Delivered",
        "items": [
            {
                "productId": 101,
                "productName": "Men's Casual Shirt",
                "quantity": 2,
                "price": 35.99,
                "totalPrice": 143.96
            },
            {
                "productId": 104,
                "productName": "Men's Running Pants",
                "quantity": 5,
                "price": 59.99,
                "totalPrice": 119.98
            },
            {
                "productId": 103,
                "productName": "Kids' Warm Jacket",
                "quantity": 2,
                "price": 49.99,
                "totalPrice": 49.99
            }
        ],
        "payment": {
            "method": "Credit Card",
            "transactionId": "TX447894442",
            "totalAmount": 313.93,
            "currency": "USD"
        }
    },
    {
        "orderId": 35,
        "customer": {
            "customerId": 1005,
            "name": "Charlie Black",
            "email": "charlieblack@example.com",
            "phone": "+1234567894",
            "address": {
                "street": "374 Main St",
                "city": "New York",
                "state": "NY",
                "zipcode": "89898",
                "country": "USA"
            }
        },
        "orderDate": "2024-10-19T21:44:17Z",
        "deliveryDate": "2024-10-25T21:44:17Z",
        "status": "Delivered",
        "items": [
            {
                "productId": 102,
                "productName": "Women's Evening Dress",
                "quantity": 4,
                "price": 89.99,
                "totalPrice": 449.95
            },
            {
                "productId": 105,
                "productName": "Women's Woolen Coat",
                "quantity": 1,
                "price": 120.0,
                "totalPrice": 360.0
            },
            {
                "productId": 104,
                "productName": "Men's Running Pants",
                "quantity": 4,
                "price": 59.99,
                "totalPrice": 119.98
            }
        ],
        "payment": {
            "method": "Cash on Delivery",
            "transactionId": "TX297283958",
            "totalAmount": 929.93,
            "currency": "USD"
        }
    },
    {
        "orderId": 36,
        "customer": {
            "customerId": 1005,
            "name": "Charlie Black",
            "email": "charlieblack@example.com",
            "phone": "+1234567894",
            "address": {
                "street": "250 Main St",
                "city": "New York",
                "state": "NY",
                "zipcode": "99152",
                "country": "USA"
            }
        },
        "orderDate": "2024-11-06T21:44:17Z",
        "deliveryDate": "2024-11-10T21:44:17Z",
        "status": "Cancelled",
        "items": [
            {
                "productId": 103,
                "productName": "Kids' Warm Jacket",
                "quantity": 1,
                "price": 49.99,
                "totalPrice": 149.97
            }
        ],
        "payment": {
            "method": "PayPal",
            "transactionId": "TX286832824",
            "totalAmount": 149.97,
            "currency": "USD"
        }
    },
    {
        "orderId": 37,
        "customer": {
            "customerId": 1001,
            "name": "John Doe",
            "email": "johndoe@example.com",
            "phone": "+1234567890",
            "address": {
                "street": "94 Main St",
                "city": "New York",
                "state": "NY",
                "zipcode": "85574",
                "country": "USA"
            }
        },
        "orderDate": "2024-10-30T21:44:17Z",
        "deliveryDate": "2024-11-08T21:44:17Z",
        "status": "Cancelled",
        "items": [
            {
                "productId": 105,
                "productName": "Women's Woolen Coat",
                "quantity": 3,
                "price": 120.0,
                "totalPrice": 240.0
            },
            {
                "productId": 102,
                "productName": "Women's Evening Dress",
                "quantity": 3,
                "price": 89.99,
                "totalPrice": 179.98
            }
        ],
        "payment": {
            "method": "PayPal",
            "transactionId": "TX277735426",
            "totalAmount": 419.98,
            "currency": "USD"
        }
    },
    {
        "orderId": 38,
        "customer": {
            "customerId": 1002,
            "name": "Jane Smith",
            "email": "janesmith@example.com",
            "phone": "+1234567891",
            "address": {
                "street": "247 Main St",
                "city": "New York",
                "state": "NY",
                "zipcode": "42158",
                "country": "USA"
            }
        },
        "orderDate": "2024-11-09T21:44:17Z",
        "deliveryDate": "2024-11-16T21:44:17Z",
        "status": "Delivered",
        "items": [
            {
                "productId": 101,
                "productName": "Men's Casual Shirt",
                "quantity": 5,
                "price": 35.99,
                "totalPrice": 35.99
            },
            {
                "productId": 105,
                "productName": "Women's Woolen Coat",
                "quantity": 4,
                "price": 120.0,
                "totalPrice": 600.0
            },
            {
                "productId": 102,
                "productName": "Women's Evening Dress",
                "quantity": 2,
                "price": 89.99,
                "totalPrice": 449.95
            }
        ],
        "payment": {
            "method": "PayPal",
            "transactionId": "TX487662847",
            "totalAmount": 1085.94,
            "currency": "USD"
        }
    },
    {
        "orderId": 39,
        "customer": {
            "customerId": 1003,
            "name": "Alice Brown",
            "email": "alicebrown@example.com",
            "phone": "+1234567892",
            "address": {
                "street": "469 Main St",
                "city": "New York",
                "state": "NY",
                "zipcode": "83833",
                "country": "USA"
            }
        },
        "orderDate": "2024-11-13T21:44:17Z",
        "deliveryDate": "2024-11-20T21:44:17Z",
        "status": "Cancelled",
        "items": [
            {
                "productId": 102,
                "productName": "Women's Evening Dress",
                "quantity": 3,
                "price": 89.99,
                "totalPrice": 89.99
            },
            {
                "productId": 103,
                "productName": "Kids' Warm Jacket",
                "quantity": 3,
                "price": 49.99,
                "totalPrice": 199.96
            },
            {
                "productId": 101,
                "productName": "Men's Casual Shirt",
                "quantity": 4,
                "price": 35.99,
                "totalPrice": 71.98
            }
        ],
        "payment": {
            "method": "Cash on Delivery",
            "transactionId": "TX886361884",
            "totalAmount": 361.93,
            "currency": "USD"
        }
    },
    {
        "orderId": 40,
        "customer": {
            "customerId": 1002,
            "name": "Jane Smith",
            "email": "janesmith@example.com",
            "phone": "+1234567891",
            "address": {
                "street": "623 Main St",
                "city": "New York",
                "state": "NY",
                "zipcode": "98781",
                "country": "USA"
            }
        },
        "orderDate": "2024-10-24T21:44:17Z",
        "deliveryDate": "2024-10-27T21:44:17Z",
        "status": "Delivered",
        "items": [
            {
                "productId": 102,
                "productName": "Women's Evening Dress",
                "quantity": 2,
                "price": 89.99,
                "totalPrice": 269.97
            },
            {
                "productId": 103,
                "productName": "Kids' Warm Jacket",
                "quantity": 1,
                "price": 49.99,
                "totalPrice": 149.97
            },
            {
                "productId": 104,
                "productName": "Men's Running Pants",
                "quantity": 3,
                "price": 59.99,
                "totalPrice": 299.95
            }
        ],
        "payment": {
            "method": "Credit Card",
            "transactionId": "TX296987533",
            "totalAmount": 719.89,
            "currency": "USD"
        }
    },
    {
        "orderId": 41,
        "customer": {
            "customerId": 1002,
            "name": "Jane Smith",
            "email": "janesmith@example.com",
            "phone": "+1234567891",
            "address": {
                "street": "265 Main St",
                "city": "New York",
                "state": "NY",
                "zipcode": "59767",
                "country": "USA"
            }
        },
        "orderDate": "2024-10-20T21:44:17Z",
        "deliveryDate": "2024-10-28T21:44:17Z",
        "status": "Shipped",
        "items": [
            {
                "productId": 104,
                "productName": "Men's Running Pants",
                "quantity": 4,
                "price": 59.99,
                "totalPrice": 59.99
            }
        ],
        "payment": {
            "method": "Credit Card",
            "transactionId": "TX698002599",
            "totalAmount": 59.99,
            "currency": "USD"
        }
    },
    {
        "orderId": 42,
        "customer": {
            "customerId": 1003,
            "name": "Alice Brown",
            "email": "alicebrown@example.com",
            "phone": "+1234567892",
            "address": {
                "street": "986 Main St",
                "city": "New York",
                "state": "NY",
                "zipcode": "80555",
                "country": "USA"
            }
        },
        "orderDate": "2024-11-06T21:44:17Z",
        "deliveryDate": "2024-11-11T21:44:17Z",
        "status": "Cancelled",
        "items": [
            {
                "productId": 102,
                "productName": "Women's Evening Dress",
                "quantity": 3,
                "price": 89.99,
                "totalPrice": 269.97
            },
            {
                "productId": 103,
                "productName": "Kids' Warm Jacket",
                "quantity": 4,
                "price": 49.99,
                "totalPrice": 99.98
            }
        ],
        "payment": {
            "method": "PayPal",
            "transactionId": "TX800671558",
            "totalAmount": 369.95,
            "currency": "USD"
        }
    },
    {
        "orderId": 43,
        "customer": {
            "customerId": 1003,
            "name": "Alice Brown",
            "email": "alicebrown@example.com",
            "phone": "+1234567892",
            "address": {
                "street": "63 Main St",
                "city": "New York",
                "state": "NY",
                "zipcode": "63790",
                "country": "USA"
            }
        },
        "orderDate": "2024-10-20T21:44:17Z",
        "deliveryDate": "2024-10-29T21:44:17Z",
        "status": "Cancelled",
        "items": [
            {
                "productId": 101,
                "productName": "Men's Casual Shirt",
                "quantity": 5,
                "price": 35.99,
                "totalPrice": 71.98
            },
            {
                "productId": 102,
                "productName": "Women's Evening Dress",
                "quantity": 2,
                "price": 89.99,
                "totalPrice": 89.99
            }
        ],
        "payment": {
            "method": "PayPal",
            "transactionId": "TX553720590",
            "totalAmount": 161.97,
            "currency": "USD"
        }
    },
    {
        "orderId": 44,
        "customer": {
            "customerId": 1002,
            "name": "Jane Smith",
            "email": "janesmith@example.com",
            "phone": "+1234567891",
            "address": {
                "street": "699 Main St",
                "city": "New York",
                "state": "NY",
                "zipcode": "93786",
                "country": "USA"
            }
        },
        "orderDate": "2024-11-12T21:44:17Z",
        "deliveryDate": "2024-11-21T21:44:17Z",
        "status": "Cancelled",
        "items": [
            {
                "productId": 104,
                "productName": "Men's Running Pants",
                "quantity": 5,
                "price": 59.99,
                "totalPrice": 59.99
            },
            {
                "productId": 101,
                "productName": "Men's Casual Shirt",
                "quantity": 5,
                "price": 35.99,
                "totalPrice": 107.97
            }
        ],
        "payment": {
            "method": "PayPal",
            "transactionId": "TX408111450",
            "totalAmount": 167.96,
            "currency": "USD"
        }
    },
    {
        "orderId": 45,
        "customer": {
            "customerId": 1004,
            "name": "Bob White",
            "email": "bobwhite@example.com",
            "phone": "+1234567893",
            "address": {
                "street": "362 Main St",
                "city": "New York",
                "state": "NY",
                "zipcode": "55944",
                "country": "USA"
            }
        },
        "orderDate": "2024-10-26T21:44:17Z",
        "deliveryDate": "2024-11-05T21:44:17Z",
        "status": "Shipped",
        "items": [
            {
                "productId": 102,
                "productName": "Women's Evening Dress",
                "quantity": 1,
                "price": 89.99,
                "totalPrice": 179.98
            }
        ],
        "payment": {
            "method": "Cash on Delivery",
            "transactionId": "TX340486125",
            "totalAmount": 179.98,
            "currency": "USD"
        }
    },
    {
        "orderId": 46,
        "customer": {
            "customerId": 1002,
            "name": "Jane Smith",
            "email": "janesmith@example.com",
            "phone": "+1234567891",
            "address": {
                "street": "510 Main St",
                "city": "New York",
                "state": "NY",
                "zipcode": "13007",
                "country": "USA"
            }
        },
        "orderDate": "2024-11-08T21:44:17Z",
        "deliveryDate": "2024-11-13T21:44:17Z",
        "status": "Cancelled",
        "items": [
            {
                "productId": 105,
                "productName": "Women's Woolen Coat",
                "quantity": 1,
                "price": 120.0,
                "totalPrice": 360.0
            }
        ],
        "payment": {
            "method": "Cash on Delivery",
            "transactionId": "TX667721383",
            "totalAmount": 360.0,
            "currency": "USD"
        }
    },
    {
        "orderId": 47,
        "customer": {
            "customerId": 1002,
            "name": "Jane Smith",
            "email": "janesmith@example.com",
            "phone": "+1234567891",
            "address": {
                "street": "825 Main St",
                "city": "New York",
                "state": "NY",
                "zipcode": "91142",
                "country": "USA"
            }
        },
        "orderDate": "2024-11-06T21:44:17Z",
        "deliveryDate": "2024-11-12T21:44:17Z",
        "status": "Shipped",
        "items": [
            {
                "productId": 101,
                "productName": "Men's Casual Shirt",
                "quantity": 3,
                "price": 35.99,
                "totalPrice": 143.96
            },
            {
                "productId": 102,
                "productName": "Women's Evening Dress",
                "quantity": 5,
                "price": 89.99,
                "totalPrice": 449.95
            },
            {
                "productId": 103,
                "productName": "Kids' Warm Jacket",
                "quantity": 5,
                "price": 49.99,
                "totalPrice": 49.99
            }
        ],
        "payment": {
            "method": "PayPal",
            "transactionId": "TX165778025",
            "totalAmount": 643.9,
            "currency": "USD"
        }
    },
    {
        "orderId": 48,
        "customer": {
            "customerId": 1004,
            "name": "Bob White",
            "email": "bobwhite@example.com",
            "phone": "+1234567893",
            "address": {
                "street": "959 Main St",
                "city": "New York",
                "state": "NY",
                "zipcode": "37095",
                "country": "USA"
            }
        },
        "orderDate": "2024-10-31T21:44:17Z",
        "deliveryDate": "2024-11-06T21:44:17Z",
        "status": "Shipped",
        "items": [
            {
                "productId": 105,
                "productName": "Women's Woolen Coat",
                "quantity": 5,
                "price": 120.0,
                "totalPrice": 240.0
            },
            {
                "productId": 103,
                "productName": "Kids' Warm Jacket",
                "quantity": 5,
                "price": 49.99,
                "totalPrice": 199.96
            }
        ],
        "payment": {
            "method": "Cash on Delivery",
            "transactionId": "TX389665008",
            "totalAmount": 439.96,
            "currency": "USD"
        }
    },
    {
        "orderId": 49,
        "customer": {
            "customerId": 1003,
            "name": "Alice Brown",
            "email": "alicebrown@example.com",
            "phone": "+1234567892",
            "address": {
                "street": "189 Main St",
                "city": "New York",
                "state": "NY",
                "zipcode": "22080",
                "country": "USA"
            }
        },
        "orderDate": "2024-10-22T21:44:17Z",
        "deliveryDate": "2024-10-25T21:44:17Z",
        "status": "Pending",
        "items": [
            {
                "productId": 104,
                "productName": "Men's Running Pants",
                "quantity": 3,
                "price": 59.99,
                "totalPrice": 239.96
            }
        ],
        "payment": {
            "method": "PayPal",
            "transactionId": "TX739626114",
            "totalAmount": 239.96,
            "currency": "USD"
        }
    },
    {
        "orderId": 50,
        "customer": {
            "customerId": 1002,
            "name": "Jane Smith",
            "email": "janesmith@example.com",
            "phone": "+1234567891",
            "address": {
                "street": "739 Main St",
                "city": "New York",
                "state": "NY",
                "zipcode": "30892",
                "country": "USA"
            }
        },
        "orderDate": "2024-10-20T21:44:17Z",
        "deliveryDate": "2024-10-27T21:44:17Z",
        "status": "Delivered",
        "items": [
            {
                "productId": 103,
                "productName": "Kids' Warm Jacket",
                "quantity": 5,
                "price": 49.99,
                "totalPrice": 199.96
            }
        ],
        "payment": {
            "method": "PayPal",
            "transactionId": "TX493526820",
            "totalAmount": 199.96,
            "currency": "USD"
        }
    }
]